aioskd/__init__.py
aioskd/cli.py
aioskd/scheduler.py
aioskd-0.0.8.dist-info/LICENSE
aioskd-0.0.8.dist-info/METADATA
aioskd-0.0.8.dist-info/WHEEL
aioskd-0.0.8.dist-info/entry_points.txt
aioskd-0.0.8.dist-info/top_level.txt
aioskd-0.0.8.dist-info/RECORD
