Metadata-Version: 2.2
Name: aioskd
Version: 0.0.8
Summary: Tool for execute async background tasks
Author: Artem Sydorenko
Author-email: kradworkmail@gmail.com
Keywords: async,scheduling,background-tasks,asynchronous-programming,scheduler-library,python,task-scheduler,background-processing,concurrency,asyncio,timed-tasks,library,python3,interval-tasks,task-scheduling,asynchronous-background-tasks,background-scheduler,background-jobs,background-execution,task-execution,scheduling-tasks,async-jobs,async-tasks,job-scheduler,task-runner,task-manager
Classifier: Programming Language :: Python :: 3.11
Requires-Python: >=3.11
License-File: LICENSE
Requires-Dist: click==8.1.3
Dynamic: author
Dynamic: author-email
Dynamic: classifier
Dynamic: description
Dynamic: description-content-type
Dynamic: keywords
Dynamic: requires-dist
Dynamic: requires-python
Dynamic: summary
